<elements><element><elementIndex>1</elementIndex><elementType>object</elementType><componentRender>1</componentRender><properties><property><propertyName>position</propertyName><propertyValue>absolute</propertyValue></property><property><propertyName>top</propertyName><propertyValue>200</propertyValue></property><property><propertyName>left</propertyName><propertyValue>300</propertyValue></property></properties></element><element><elementIndex>2</elementIndex><elementType>component</elementType><componentRender>1</componentRender><root>Box</root><properties><property><propertyName>name</propertyName><propertyValue>THIS IS A BOX</propertyValue></property><property><propertyName>style</propertyName><propertyElement>1</propertyElement></property></properties><children/></element><element><elementIndex>3</elementIndex><elementType>component</elementType><componentRender>1</componentRender><componentRoot>1</componentRoot><root>Container</root><properties/><children><child><childIndex>1</childIndex><childElement>2</childElement></child></children></element><element><elementType>placeholder</elementType><componentName>_</componentName><componentRender>_</componentRender><componentRoot>_</componentRoot><root>_</root><children><child><childIndex>_</childIndex><childElement>_</childElement><childValue>_</childValue><childType>_</childType></child></children><properties><property><propertyName>_</propertyName><propertyElement>_</propertyElement><propertyValue>_</propertyValue><propertyType>_</propertyType></property></properties><val><valElement>_</valElement><valValue>_</valValue><valType>_</valType></val><index><indexElement>_</indexElement><indexValue>_</indexValue><indexType>_</indexType></index><in><inElement>_</inElement><inValue>_</inValue><inType>_</inType></in><for><forElement>_</forElement><forValue>_</forValue><forType>_</forType></for><do><doElement>_</doElement><doValue>_</doValue><doType>_</doType></do><if><ifElement>_</ifElement><ifValue>_</ifValue><ifType>_</ifType></if><then><thenElement>_</thenElement><thenValue>_</thenValue><thenType>_</thenType></then><else><elseElement>_</elseElement><elseValue>_</elseValue><elseType>_</elseType></else><merge><mergeElement>_</mergeElement><mergeValue>_</mergeValue><mergeType>_</mergeType></merge></element></elements>